[{"datetime":"13:29:54","g_value":34,"lat":"44.884495","long":"11.613286"},{"datetime":"13:30:11","g_value":31,"lat":"44.884766","long":"11.612547"},{"datetime":"13:30:23","g_value":31,"lat":"44.884846","long":"11.611746"},{"datetime":"13:30:32","g_value":32,"lat":"44.884926","long":"11.611175"},{"datetime":"13:30:34","g_value":31,"lat":"44.884892","long":"11.611067"},{"datetime":"13:30:35","g_value":74,"lat":"44.884861","long":"11.611038"},{"datetime":"13:29:54","g_value":34,"lat":"44.884495","long":"11.613286"},{"datetime":"13:30:11","g_value":31,"lat":"44.884766","long":"11.612547"},{"datetime":"13:30:23","g_value":31,"lat":"44.884846","long":"11.611746"},{"datetime":"13:30:32","g_value":32,"lat":"44.884926","long":"11.611175"},{"datetime":"13:30:34","g_value":31,"lat":"44.884892","long":"11.611067"},{"datetime":"13:30:35","g_value":74,"lat":"44.884861","long":"11.611038"},{"datetime":"13:31:05","g_value":33,"lat":"44.883598","long":"11.610945"},{"datetime":"13:31:11","g_value":43,"lat":"44.883560","long":"11.611293"},{"datetime":"13:31:36","g_value":33,"lat":"44.883533","long":"11.612713"},{"datetime":"13:31:48","g_value":33,"lat":"44.883987","long":"11.613011"},{"datetime":"13:20:06","lat":44.838396,"g_value":39,"long":11.619351},{"datetime":"13:20:23","lat":44.838031,"g_value":64,"long":11.620252},{"datetime":"13:21:05","lat":44.837605,"g_value":74,"long":11.620317},{"datetime":"13:21:42","lat":44.837057,"g_value":66,"long":11.619952},{"datetime":"13:22:20","lat":44.836433,"g_value":104,"long":11.619619},{"datetime":"13:23:33","lat":44.835882,"g_value":118,"long":11.619287},{"datetime":"13:23:41","lat":44.83538,"g_value":23,"long":11.619437},{"datetime":"13:24:47","lat":44.835425,"g_value":75,"long":11.619882},{"datetime":"13:24:57","lat":44.834893,"g_value":24,"long":11.621035},{"datetime":"13:25:57","lat":44.835372,"g_value":45,"long":11.621588},{"datetime":"13:26:27","lat":44.836042,"g_value":73,"long":11.621985},{"datetime":"13:27:17","lat":44.836593,"g_value":15,"long":11.62236},{"datetime":"13:27:57","lat":44.837198,"g_value":35,"long":11.621888},{"datetime":"13:28:07","lat":44.837795,"g_value":105,"long":11.620606}]